odoo8_addon_stock_packaging_usability_ul-8.0.1.0.0-py2.7-nspkg.pth
odoo_addons/stock_packaging_usability_ul/__openerp__.py
odoo_addons/stock_packaging_usability_ul/__init__.py
odoo_addons/stock_packaging_usability_ul/README.rst
odoo_addons/stock_packaging_usability_ul/i18n/fr.po
odoo_addons/stock_packaging_usability_ul/i18n/stock_packaging_usability_ul.pot
odoo_addons/stock_packaging_usability_ul/wizard/stock_transfer_details.xml
odoo_addons/stock_packaging_usability_ul/wizard/stock_select_ul.py
odoo_addons/stock_packaging_usability_ul/wizard/stock_select_ul.xml
odoo_addons/stock_packaging_usability_ul/wizard/__init__.py
odoo8_addon_stock_packaging_usability_ul-8.0.1.0.0.dist-info/top_level.txt
odoo8_addon_stock_packaging_usability_ul-8.0.1.0.0.dist-info/WHEEL
odoo8_addon_stock_packaging_usability_ul-8.0.1.0.0.dist-info/RECORD
odoo8_addon_stock_packaging_usability_ul-8.0.1.0.0.dist-info/metadata.json
odoo8_addon_stock_packaging_usability_ul-8.0.1.0.0.dist-info/DESCRIPTION.rst
odoo8_addon_stock_packaging_usability_ul-8.0.1.0.0.dist-info/METADATA
odoo8_addon_stock_packaging_usability_ul-8.0.1.0.0.dist-info/namespace_packages.txt
